{"hash":"0e23c8c4c0f42372","route_id":"KMB_36B","route_key":"KMB_36B","direction":2,"company":"KMB/LWB","stops":[{"stop_id":"508D1C5BF90CE574","stop_name":"High Speed Rail West Kowloon Station Bus Terminus","stop_name_tc":"高鐵(西九龍站)巴士總站 (YT960)","sequence":1,"company":"KMB/LWB","lat":22.30755,"lng":114.164551,"osm_node_sequence":0,"osm_node_name":"HIGH SPEED RAIL WEST KOWLOON STATION BUS TERMINUS"},{"stop_id":"98F2067168C267FE","stop_name":"Jordan Road, High Speed Rail Station (YT242)","stop_name_tc":"佐敦道,高鐵站 (YT242)","sequence":2,"company":"KMB/LWB","lat":22.30618,"lng":114.166315,"osm_node_sequence":66,"osm_node_name":"JORDAN ROAD, HIGH SPEED RAIL STATION (YT242)"},{"stop_id":"195090E551109C0A","stop_name":"Shanghai Street, Temple Street Night Market","stop_name_tc":"上海街 廟街夜市 (YT244)","sequence":3,"company":"KMB/LWB","lat":22.305717,"lng":114.168627,"osm_node_sequence":82,"osm_node_name":"SHANGHAI STREET, TEMPLE STREET NIGHT MARKET"},{"stop_id":"4624AC39DB25D456","stop_name":"Ning Po Street Yau Ma Tei (YT128)","stop_name_tc":"油麻地寧波街 (YT128)","sequence":4,"company":"KMB/LWB","lat":22.306923,"lng":114.171377,"osm_node_sequence":116,"osm_node_name":"NING PO STREET YAU MA TEI (YT128)"},{"stop_id":"2DB47A3C263E4F5C","stop_name":"Kowloon Central Post Office (YT129)","stop_name_tc":"九龍中央郵政局 (YT129)","sequence":5,"company":"KMB/LWB","lat":22.308904,"lng":114.171181,"osm_node_sequence":128,"osm_node_name":"KOWLOON CENTRAL POST OFFICE (YT129)"},{"stop_id":"6DFEED7F0DB44298","stop_name":"Dundas Street Mong Kok (MK160)","stop_name_tc":"旺角登打士街 (MK160)","sequence":6,"company":"KMB/LWB","lat":22.315026,"lng":114.170087,"osm_node_sequence":173,"osm_node_name":"DUNDAS STREET MONG KOK (MK160)"},{"stop_id":"A6ACEA5D8F32521D","stop_name":"Nelson Street Mong Kok (MK170)","stop_name_tc":"旺角奶路臣街 (MK170)","sequence":7,"company":"KMB/LWB","lat":22.317916,"lng":114.169527,"osm_node_sequence":195,"osm_node_name":"NELSON STREET MONG KOK (MK170)"},{"stop_id":"77505F1651DFA82F","stop_name":"Kei Wing Primary School, Metropark Hotel Mong Kok","stop_name_tc":"基榮小學 維景酒店 (MK301)","sequence":8,"company":"KMB/LWB","lat":22.322581,"lng":114.168045,"osm_node_sequence":247,"osm_node_name":"KEI WING PRIMARY SCHOOL, METROPARK HOTEL MONG KOK"},{"stop_id":"69C45315DFA906FC","stop_name":"Tong Mi Road Mong Kok (MK305)","stop_name_tc":"旺角塘尾道 (MK305)","sequence":9,"company":"KMB/LWB","lat":22.324417,"lng":114.1657,"osm_node_sequence":265,"osm_node_name":"TONG MI ROAD MONG KOK (MK305)"},{"stop_id":"BE510511B0A7344E","stop_name":"Tai Nan Street (SS340)","stop_name_tc":"大南街 (SS340)","sequence":10,"company":"KMB/LWB","lat":22.32699,"lng":114.163828,"osm_node_sequence":285,"osm_node_name":"TAI NAN STREET (SS340)"},{"stop_id":"5F181A62BBCA16F7","stop_name":"Shek Kip Mei Street Rest Garden (SS331)","stop_name_tc":"石硤尾街休憩花園 (SS331)","sequence":11,"company":"KMB/LWB","lat":22.327915,"lng":114.163906,"osm_node_sequence":292,"osm_node_name":"SHEK KIP MEI STREET REST GARDEN (SS331)"},{"stop_id":"AAA29653BB050609","stop_name":"Pei Ho Street (SS334)","stop_name_tc":"北河街 (SS334)","sequence":12,"company":"KMB/LWB","lat":22.329011,"lng":114.162478,"osm_node_sequence":304,"osm_node_name":"PEI HO STREET (SS334)"},{"stop_id":"EB9E9B5EEE20114C","stop_name":"Lai Kok Estate (SS222)","stop_name_tc":"麗閣邨 (SS222)","sequence":13,"company":"KMB/LWB","lat":22.333843,"lng":114.158223,"osm_node_sequence":341,"osm_node_name":"LAI KOK ESTATE (SS222)"},{"stop_id":"0BADB28A19C2E0BE","stop_name":"Trade Square (SS228)","stop_name_tc":"貿易廣場 (SS228)","sequence":14,"company":"KMB/LWB","lat":22.33674,"lng":114.154311,"osm_node_sequence":361,"osm_node_name":"TRADE SQUARE (SS228)"},{"stop_id":"D355B700FF30B3D7","stop_name":"Hing Wah Street Cheung Sha Wan (SS229)","stop_name_tc":"長沙灣興華街 (SS229)","sequence":15,"company":"KMB/LWB","lat":22.337744,"lng":114.152954,"osm_node_sequence":369,"osm_node_name":"HING WAH STREET CHEUNG SHA WAN (SS229)"},{"stop_id":"4A1EEF2271FA16D3","stop_name":"Lai Chi Kok Station (SS239)","stop_name_tc":"荔枝角站 (SS239)","sequence":16,"company":"KMB/LWB","lat":22.337258,"lng":114.148408,"osm_node_sequence":407,"osm_node_name":"LAI CHI KOK STATION (SS239)"},{"stop_id":"B4F2BAAED2470D0A","stop_name":"Jao Tsung-I Academy (KW120)","stop_name_tc":"饒宗頤文化館 (KW120)","sequence":17,"company":"KMB/LWB","lat":22.33716,"lng":114.142131,"osm_node_sequence":453,"osm_node_name":"JAO TSUNG-I ACADEMY (KW120)"},{"stop_id":"75C0DF6C7724CEEA","stop_name":"Chung Shan Terrace (KW121)","stop_name_tc":"鐘山台 (KW121)","sequence":18,"company":"KMB/LWB","lat":22.343708,"lng":114.139414,"osm_node_sequence":514,"osm_node_name":"CHUNG SHAN TERRACE (KW121)"},{"stop_id":"EBF4EB34B96BC242","stop_name":"Wah Yuen Chuen (KW122)","stop_name_tc":"華員邨 (KW122)","sequence":19,"company":"KMB/LWB","lat":22.351321,"lng":114.132856,"osm_node_sequence":587,"osm_node_name":"WAH YUEN CHUEN (KW122)"},{"stop_id":"3FE93821145B65F5","stop_name":"Yip Shing Street Kwai Chung (KW123)","stop_name_tc":"葵涌業成街 (KW123)","sequence":20,"company":"KMB/LWB","lat":22.360158,"lng":114.13519,"osm_node_sequence":630,"osm_node_name":"YIP SHING STREET KWAI CHUNG (KW123)"},{"stop_id":"264B29FD223D9C4E","stop_name":"Ta Chuen Ping Street Kwai Chung (KW486)","stop_name_tc":"葵涌打磚坪街 (KW486)","sequence":21,"company":"KMB/LWB","lat":22.365984,"lng":114.136723,"osm_node_sequence":674,"osm_node_name":"TA CHUEN PING STREET KWAI CHUNG (KW486)"},{"stop_id":"86D7BB9BA055D8A6","stop_name":"Shek Yi Road Kwai Chung (KW487)","stop_name_tc":"葵涌石宜路 (KW487)","sequence":22,"company":"KMB/LWB","lat":22.368408,"lng":114.139187,"osm_node_sequence":699,"osm_node_name":"SHEK YI ROAD KWAI CHUNG (KW487)"},{"stop_id":"C24776F20FE877FF","stop_name":"Lam Tin Street Kwai Chung (KW489)","stop_name_tc":"葵涌藍田街 (KW489)","sequence":23,"company":"KMB/LWB","lat":22.369867,"lng":114.138528,"osm_node_sequence":717,"osm_node_name":"LAM TIN STREET KWAI CHUNG (KW489)"},{"stop_id":"257A6E19DD7F156C","stop_name":"Wo Yi Hop Road Sportsground (TW490)","stop_name_tc":"和宜合道運動場 (TW490)","sequence":24,"company":"KMB/LWB","lat":22.373954,"lng":114.136349,"osm_node_sequence":752,"osm_node_name":"WO YI HOP ROAD SPORTSGROUND (TW490)"},{"stop_id":"28A57C043C111604","stop_name":"Shek Wai Kok Sun Village (TW493)","stop_name_tc":"石圍角新村 (TW493)","sequence":25,"company":"KMB/LWB","lat":22.375875,"lng":114.13625,"osm_node_sequence":759,"osm_node_name":"SHEK WAI KOK SUN VILLAGE (TW493)"},{"stop_id":"7EFC43457A826032","stop_name":"Lei Muk Shue Bus Terminus (TW904)","stop_name_tc":"梨木樹巴士總站 (TW904)","sequence":26,"company":"KMB/LWB","lat":22.37755,"lng":114.136571,"osm_node_sequence":771,"osm_node_name":"LEI MUK SHUE BUS TERMINUS (TW904)"}],"coords":[[22.307552,114.164566],[22.307401,114.164584],[22.306919,114.164649],[22.306881,114.164641],[22.306849,114.164615],[22.306829,114.164573],[22.306827,114.164523],[22.306848,114.16448],[22.306887,114.16445],[22.306926,114.164443],[22.306962,114.164452],[22.306993,114.164483],[22.30702,114.164517],[22.307056,114.164542],[22.307102,114.164553],[22.307135,114.164548],[22.307359,114.164521],[22.307519,114.164501],[22.307676,114.164481],[22.307819,114.164463],[22.307892,114.164446],[22.307916,114.164437],[22.307986,114.16441],[22.308093,114.164348],[22.308145,114.164312],[22.308218,114.16428],[22.308317,114.164252],[22.308982,114.16408],[22.309068,114.164065],[22.309136,114.16406],[22.309225,114.164074],[22.30928,114.164126],[22.309305,114.164204],[22.309244,114.164629],[22.309219,114.164808],[22.309214,114.164845],[22.309211,114.164868],[22.309203,114.164917],[22.309197,114.164957],[22.309181,114.165067],[22.309166,114.165154],[22.309153,114.165225],[22.309032,114.16521],[22.308933,114.16519],[22.3089,114.165182],[22.308782,114.16515],[22.308678,114.165117],[22.308594,114.165106],[22.30845,114.16507],[22.30819,114.165033],[22.308165,114.165031],[22.307875,114.165023],[22.307745,114.165017],[22.307423,114.165021],[22.3071,114.165054],[22.306919,114.165074],[22.306824,114.1651],[22.306713,114.165145],[22.30654,114.165302],[22.306461,114.165374],[22.306316,114.165504],[22.306222,114.165955],[22.306173,114.166112],[22.306155,114.166191],[22.30614,114.166254],[22.306134,114.166282],[22.306129,114.1663],[22.306126,114.166314],[22.306028,114.166723],[22.305993,114.166869],[22.305981,114.166913],[22.305967,114.166958],[22.305942,114.167021],[22.30592,114.167082],[22.305902,114.167149],[22.305897,114.167189],[22.305883,114.167446],[22.305879,114.167482],[22.305857,114.167613],[22.30579,114.167972],[22.305744,114.168226],[22.305701,114.168436],[22.30566,114.168611],[22.305637,114.168707],[22.305631,114.16873],[22.305603,114.168847],[22.305575,114.168965],[22.305553,114.169059],[22.305545,114.169095],[22.3055,114.16927],[22.30547,114.169403],[22.305459,114.169444],[22.305396,114.169694],[22.305383,114.169771],[22.305359,114.169913],[22.305324,114.170137],[22.305298,114.170352],[22.305291,114.170528],[22.305289,114.170591],[22.305288,114.170711],[22.305287,114.170841],[22.3053,114.171093],[22.30534,114.171407],[22.305342,114.171423],[22.305346,114.171449],[22.305366,114.171569],[22.305528,114.171553],[22.305938,114.171514],[22.306135,114.171495],[22.306187,114.17149],[22.306325,114.171477],[22.306417,114.171468],[22.306535,114.171457],[22.306665,114.171445],[22.306727,114.171438],[22.306882,114.171423],[22.306927,114.171418],[22.306927,114.171418],[22.307095,114.171415],[22.30747,114.171379],[22.307719,114.171344],[22.308214,114.171297],[22.308266,114.171292],[22.308317,114.171287],[22.308412,114.171278],[22.308489,114.171271],[22.308729,114.171244],[22.308852,114.17123],[22.308908,114.171224],[22.308994,114.171214],[22.309087,114.171204],[22.309267,114.171186],[22.309363,114.171176],[22.309606,114.17115],[22.309716,114.171139],[22.310075,114.171111],[22.310133,114.171107],[22.310204,114.171101],[22.310275,114.171095],[22.310708,114.171054],[22.310748,114.171048],[22.310762,114.171046],[22.310815,114.171038],[22.310922,114.171017],[22.31122,114.170958],[22.311342,114.170935],[22.311396,114.170924],[22.31147,114.170909],[22.311525,114.170898],[22.311539,114.170896],[22.311705,114.170863],[22.311753,114.170853],[22.31184,114.170835],[22.312658,114.170675],[22.312865,114.170634],[22.312876,114.170632],[22.312947,114.170618],[22.313035,114.170602],[22.313149,114.170579],[22.313253,114.170558],[22.313284,114.170551],[22.313653,114.170476],[22.313862,114.170431],[22.314004,114.170402],[22.314047,114.170393],[22.314199,114.170361],[22.314287,114.170343],[22.314411,114.17032],[22.31455,114.170295],[22.314629,114.170281],[22.314873,114.170229],[22.314944,114.170214],[22.315014,114.170198],[22.315045,114.170191],[22.315283,114.170141],[22.315362,114.170125],[22.315449,114.170106],[22.31569,114.170055],[22.3158,114.170031],[22.315932,114.170003],[22.315945,114.17],[22.316066,114.169976],[22.316297,114.169931],[22.3165,114.169888],[22.316537,114.16988],[22.316679,114.169852],[22.316763,114.169835],[22.316815,114.169824],[22.317,114.169786],[22.317079,114.169769],[22.317354,114.16971],[22.317407,114.169698],[22.317427,114.169693],[22.317601,114.169659],[22.317863,114.169609],[22.317927,114.169597],[22.317927,114.169597],[22.317975,114.169587],[22.318091,114.169563],[22.318186,114.169544],[22.318229,114.169535],[22.318353,114.169509],[22.318366,114.169507],[22.318402,114.1695],[22.31854,114.169473],[22.318693,114.169441],[22.31882,114.169415],[22.319065,114.169365],[22.319144,114.169348],[22.319197,114.169338],[22.319293,114.16932],[22.31937,114.169302],[22.319433,114.169289],[22.319482,114.169279],[22.319662,114.169242],[22.319675,114.169239],[22.319834,114.169207],[22.319935,114.169187],[22.319971,114.16918],[22.320081,114.169158],[22.320229,114.169129],[22.320378,114.169092],[22.320536,114.169061],[22.320576,114.169053],[22.320613,114.169044],[22.320644,114.169038],[22.32072,114.169022],[22.320822,114.169],[22.320886,114.168987],[22.320944,114.168975],[22.320979,114.168968],[22.321291,114.168904],[22.321465,114.168867],[22.321557,114.16885],[22.321667,114.168836],[22.32174,114.168822],[22.321757,114.168818],[22.32185,114.1688],[22.322045,114.168762],[22.322121,114.168745],[22.322184,114.168686],[22.32227,114.16861],[22.322371,114.168514],[22.32246,114.168404],[22.322488,114.168363],[22.322601,114.168198],[22.322633,114.168151],[22.322662,114.168108],[22.322675,114.168088],[22.322726,114.168014],[22.322857,114.167821],[22.323091,114.16751],[22.323123,114.167468],[22.323269,114.167286],[22.323524,114.166937],[22.323545,114.16691],[22.323567,114.16688],[22.32362,114.166814],[22.323663,114.166756],[22.323752,114.166631],[22.323838,114.16649],[22.323925,114.166376],[22.324116,114.166139],[22.324226,114.166005],[22.324408,114.165768],[22.324443,114.165724],[22.32453,114.165612],[22.324679,114.165425],[22.324841,114.165275],[22.324975,114.1651],[22.325001,114.165066],[22.325161,114.164872],[22.325192,114.164823],[22.325236,114.164742],[22.325509,114.164394],[22.325675,114.164185],[22.325731,114.164107],[22.325811,114.164003],[22.326138,114.163573],[22.326261,114.163411],[22.326335,114.163308],[22.326408,114.16341],[22.32649,114.163483],[22.326797,114.16376],[22.326878,114.163832],[22.326943,114.16389],[22.327004,114.163945],[22.327191,114.164113],[22.327521,114.164406],[22.327597,114.164474],[22.327665,114.164386],[22.32794,114.164026],[22.327984,114.163968],[22.328002,114.163945],[22.328101,114.163817],[22.328163,114.163735],[22.328226,114.163653],[22.328417,114.163404],[22.328656,114.163092],[22.328679,114.163062],[22.328733,114.162991],[22.328854,114.162841],[22.328892,114.162792],[22.329075,114.162552],[22.329082,114.162543],[22.329156,114.162448],[22.329437,114.16209],[22.329458,114.162063],[22.329531,114.161975],[22.329838,114.161581],[22.329916,114.16148],[22.330069,114.161286],[22.330099,114.161248],[22.330202,114.161107],[22.330575,114.160631],[22.330811,114.160329],[22.330862,114.160262],[22.330943,114.16016],[22.331216,114.160407],[22.331252,114.16044],[22.331609,114.160765],[22.331648,114.160802],[22.331747,114.16089],[22.331815,114.160799],[22.33183,114.160781],[22.332065,114.160479],[22.33228,114.160209],[22.332404,114.160036],[22.332511,114.159899],[22.332577,114.159813],[22.332722,114.159628],[22.332899,114.159401],[22.332944,114.159343],[22.333118,114.159119],[22.333129,114.159105],[22.33316,114.159066],[22.333304,114.158881],[22.333338,114.158837],[22.333558,114.158554],[22.33361,114.158487],[22.333752,114.158305],[22.333827,114.158208],[22.333934,114.158069],[22.334251,114.157658],[22.334396,114.157477],[22.334432,114.157431],[22.334522,114.157311],[22.334601,114.157209],[22.334696,114.157094],[22.335005,114.156694],[22.335112,114.156556],[22.3353,114.156314],[22.335331,114.156273],[22.335588,114.155942],[22.335671,114.155836],[22.335767,114.155712],[22.335863,114.155589],[22.335987,114.155429],[22.336132,114.155242],[22.336169,114.155194],[22.336241,114.155103],[22.336803,114.154368],[22.336814,114.154354],[22.336846,114.154313],[22.337223,114.153821],[22.337251,114.153786],[22.337356,114.153652],[22.337429,114.153555],[22.337734,114.153156],[22.33783,114.153031],[22.337861,114.152991],[22.337872,114.152977],[22.337976,114.15284],[22.33801,114.152795],[22.338083,114.152698],[22.338223,114.152506],[22.338288,114.152393],[22.338331,114.152304],[22.338343,114.152281],[22.338377,114.152197],[22.338419,114.152019],[22.338427,114.151893],[22.338426,114.151847],[22.338423,114.151761],[22.338409,114.15167],[22.338372,114.151504],[22.338294,114.15126],[22.338262,114.151159],[22.338218,114.151022],[22.338188,114.150927],[22.33814,114.150771],[22.338094,114.150628],[22.338081,114.150596],[22.338068,114.150562],[22.337987,114.150316],[22.337925,114.150129],[22.337884,114.150006],[22.337855,114.149919],[22.337766,114.149651],[22.337752,114.149611],[22.337676,114.149414],[22.337633,114.149295],[22.337462,114.148795],[22.337419,114.148668],[22.3374,114.148613],[22.337381,114.148558],[22.337336,114.148426],[22.337321,114.148382],[22.337292,114.1483],[22.337209,114.148058],[22.337186,114.147994],[22.337124,114.147816],[22.337047,114.147577],[22.337033,114.147538],[22.33699,114.147415],[22.336948,114.147294],[22.336887,114.147116],[22.336843,114.146991],[22.336717,114.146637],[22.336668,114.146509],[22.336654,114.146426],[22.336636,114.146331],[22.336575,114.146149],[22.336497,114.145918],[22.336344,114.145465],[22.336306,114.145278],[22.336287,114.145119],[22.336284,114.145041],[22.336288,114.144951],[22.336301,114.14486],[22.33633,114.144751],[22.33637,114.144663],[22.33643,114.144574],[22.336649,114.144325],[22.336723,114.144206],[22.336771,114.144068],[22.336793,114.143924],[22.3368,114.143833],[22.336803,114.14374],[22.336805,114.143629],[22.336815,114.143385],[22.336815,114.143287],[22.33682,114.143166],[22.336828,114.143064],[22.336843,114.142951],[22.336868,114.142822],[22.336894,114.142696],[22.336929,114.142562],[22.336966,114.142453],[22.33701,114.142367],[22.33705,114.142301],[22.337089,114.142244],[22.337166,114.142153],[22.337173,114.142147],[22.337206,114.142116],[22.337255,114.142081],[22.337336,114.142027],[22.337412,114.141985],[22.337777,114.141781],[22.337874,114.141725],[22.337895,114.141714],[22.337934,114.141691],[22.338268,114.141503],[22.338341,114.141468],[22.33841,114.141441],[22.338481,114.141422],[22.338554,114.141407],[22.338627,114.141397],[22.338696,114.141394],[22.338772,114.141398],[22.338853,114.14141],[22.338915,114.141428],[22.338977,114.141451],[22.33904,114.141476],[22.339103,114.14151],[22.339161,114.141549],[22.339245,114.141613],[22.339373,114.141707],[22.339457,114.141763],[22.339545,114.141819],[22.339613,114.141857],[22.339676,114.141886],[22.33975,114.141911],[22.339818,114.141925],[22.339904,114.141934],[22.339984,114.141934],[22.340037,114.141924],[22.340073,114.141918],[22.340126,114.141906],[22.340188,114.141885],[22.340286,114.141832],[22.340432,114.141719],[22.340488,114.141677],[22.340527,114.141649],[22.340559,114.141625],[22.340627,114.141588],[22.340797,114.141454],[22.340844,114.141418],[22.340966,114.141317],[22.34118,114.141159],[22.341327,114.141076],[22.341437,114.140993],[22.341508,114.14092],[22.341818,114.140684],[22.341902,114.140618],[22.342109,114.140468],[22.342222,114.140392],[22.342341,114.140319],[22.342643,114.140147],[22.343343,114.139762],[22.343432,114.139708],[22.343513,114.139651],[22.343584,114.139593],[22.343666,114.139519],[22.343738,114.139451],[22.343738,114.139451],[22.343782,114.139411],[22.343844,114.13935],[22.343869,114.139324],[22.343906,114.139282],[22.343939,114.139242],[22.343969,114.139204],[22.344007,114.13916],[22.344053,114.139114],[22.344188,114.138987],[22.344244,114.138935],[22.344309,114.13888],[22.344376,114.138829],[22.344449,114.138778],[22.344522,114.138736],[22.344618,114.138688],[22.344712,114.13865],[22.344807,114.138618],[22.344905,114.13859],[22.345044,114.138558],[22.345133,114.13854],[22.345227,114.138527],[22.345397,114.13851],[22.345982,114.138454],[22.346134,114.138439],[22.346232,114.138427],[22.346334,114.138413],[22.34643,114.138392],[22.346513,114.138366],[22.346593,114.138331],[22.346668,114.138283],[22.346726,114.138236],[22.346782,114.138181],[22.346842,114.138111],[22.34691,114.138002],[22.346964,114.137888],[22.346999,114.137788],[22.347028,114.137682],[22.34719,114.137008],[22.347349,114.136337],[22.347376,114.136253],[22.347418,114.136162],[22.347467,114.136084],[22.347514,114.136022],[22.347564,114.13597],[22.34763,114.135916],[22.347709,114.135863],[22.347949,114.135714],[22.348086,114.135632],[22.348178,114.135577],[22.348274,114.13551],[22.348338,114.135457],[22.348406,114.13539],[22.348475,114.135313],[22.348547,114.135227],[22.348609,114.135145],[22.349501,114.134014],[22.349699,114.133759],[22.349799,114.13363],[22.349907,114.133496],[22.349988,114.133417],[22.350079,114.133337],[22.350176,114.133263],[22.35026,114.133205],[22.350372,114.133141],[22.350468,114.133097],[22.350611,114.133041],[22.350744,114.133003],[22.350863,114.132976],[22.350981,114.132962],[22.351082,114.132953],[22.351292,114.132944],[22.351322,114.132944],[22.351442,114.132943],[22.352023,114.132936],[22.352277,114.132931],[22.352556,114.132929],[22.352672,114.132929],[22.352797,114.132937],[22.353169,114.132971],[22.353499,114.133003],[22.353786,114.13304],[22.354044,114.133073],[22.35437,114.133115],[22.354744,114.133163],[22.354822,114.133175],[22.3549,114.13319],[22.354983,114.133212],[22.355049,114.133232],[22.355125,114.13326],[22.355202,114.133291],[22.355282,114.133328],[22.355363,114.133368],[22.355731,114.133558],[22.355787,114.133585],[22.355853,114.133613],[22.355924,114.133641],[22.355993,114.133665],[22.356084,114.133692],[22.356202,114.133716],[22.35644,114.133752],[22.356722,114.133788],[22.357444,114.133886],[22.358056,114.133977],[22.358276,114.134015],[22.358499,114.134078],[22.358688,114.134155],[22.358924,114.134279],[22.359115,114.134391],[22.359157,114.134423],[22.359308,114.134539],[22.359423,114.134639],[22.359574,114.13478],[22.359817,114.135025],[22.360041,114.135245],[22.360081,114.135284],[22.360449,114.135636],[22.360598,114.135763],[22.360773,114.135885],[22.360901,114.13596],[22.361031,114.136013],[22.361075,114.136032],[22.361277,114.136078],[22.361535,114.13613],[22.361612,114.136136],[22.361714,114.136138],[22.361784,114.136132],[22.362049,114.136102],[22.36223,114.13606],[22.36232,114.136047],[22.362386,114.136039],[22.362466,114.136033],[22.362553,114.136043],[22.362697,114.136025],[22.363131,114.135973],[22.363714,114.135896],[22.363794,114.135882],[22.364005,114.135838],[22.364169,114.135789],[22.364405,114.135688],[22.364524,114.135642],[22.364628,114.135598],[22.364759,114.135546],[22.364831,114.135514],[22.364945,114.135464],[22.364998,114.135441],[22.365027,114.13545],[22.365044,114.135461],[22.365056,114.135476],[22.365071,114.135502],[22.365169,114.135669],[22.36518,114.135685],[22.365402,114.136028],[22.36542,114.136057],[22.365469,114.136136],[22.36553,114.136237],[22.365673,114.136474],[22.365685,114.136494],[22.36582,114.136697],[22.365924,114.136624],[22.365941,114.136612],[22.366455,114.136206],[22.366748,114.135982],[22.366892,114.135872],[22.367072,114.135762],[22.367143,114.135728],[22.367251,114.135715],[22.36737,114.135733],[22.367471,114.135778],[22.367552,114.135853],[22.367749,114.136154],[22.367888,114.136451],[22.368113,114.137221],[22.368149,114.137449],[22.368237,114.137971],[22.368242,114.138161],[22.36823,114.138253],[22.368212,114.138314],[22.368104,114.138489],[22.368077,114.13853],[22.367743,114.138997],[22.367699,114.139068],[22.367799,114.13911],[22.367913,114.139157],[22.368397,114.139254],[22.368407,114.139256],[22.368514,114.139276],[22.368682,114.139307],[22.368872,114.139333],[22.368936,114.13933],[22.368985,114.139316],[22.369005,114.139309],[22.369037,114.139298],[22.369052,114.139292],[22.369108,114.139268],[22.369172,114.139224],[22.36933,114.139059],[22.369344,114.139041],[22.369402,114.13897],[22.369494,114.138859],[22.36958,114.13876],[22.369718,114.138602],[22.369814,114.138479],[22.369826,114.138464],[22.370042,114.138205],[22.370138,114.138036],[22.370188,114.137977],[22.370416,114.137709],[22.370431,114.137691],[22.370589,114.137539],[22.370695,114.137397],[22.370714,114.137371],[22.370966,114.137027],[22.371019,114.136957],[22.371133,114.136821],[22.371221,114.136738],[22.371233,114.136726],[22.371418,114.136578],[22.371622,114.136494],[22.371742,114.136444],[22.371865,114.136363],[22.372021,114.136203],[22.372069,114.136147],[22.372145,114.136055],[22.372198,114.136104],[22.372266,114.136158],[22.372347,114.136207],[22.372449,114.136266],[22.372487,114.136285],[22.372516,114.136302],[22.372589,114.136345],[22.372636,114.136375],[22.37271,114.136387],[22.372788,114.136392],[22.373078,114.136387],[22.373124,114.136387],[22.373192,114.136387],[22.373954,114.136382],[22.374216,114.13638],[22.374318,114.136379],[22.375013,114.136371],[22.375144,114.136369],[22.375624,114.13638],[22.375772,114.136388],[22.375849,114.136403],[22.375963,114.136426],[22.37617,114.136469],[22.376193,114.136472],[22.376262,114.136484],[22.376369,114.136509],[22.376462,114.13653],[22.376493,114.136538],[22.376543,114.136553],[22.376563,114.136558],[22.376678,114.136595],[22.376827,114.13665],[22.377452,114.136881]]}